[
    {
        "id": 1,
        "name": "Carlos Enrique Duarte Ortiz",
        "email": "carlosduarte.1@hotmail.com"
    },
    {
        "id": 2,
        "name": "Carlos Luis Duarte Ortiz",
        "email": "carlosluis.1@hotmail.com"
    },
    {
        "id": 3,
        "name": "Carlos Roberto Duarte Ortiz",
        "email": "carlosroberto.1@hotmail.com"
    },
    {
        "id": 4,
        "name": "Carlos Antonio Duarte Ortiz",
        "email": "carlosantonio.1@hotmail.com"
    },
    {
        "id": 5,
        "name": "Carlos Felípe Duarte Ortiz",
        "email": "carlosfelipe.1@hotmail.com"
    },
    {
        "id": 6,
        "name": "Carlos Juan Duarte Ortiz",
        "email": "carlosjuan.1@hotmail.com"
    },
    {
        "id": 7,
        "name": "Andrés Enrique Duarte Ortiz",
        "email": "andresenrique.1@hotmail.com"
    },
    {
        "id": 8,
        "name": "Carlos Rigoberto Duarte Ortiz",
        "email": "carlosrigoberto.1@hotmail.com"
    },
    {
        "id": 9,
        "name": "Carlos Ezequiel Duarte Ortiz",
        "email": "carlosezequiel.1@hotmail.com"
    },
    {
        "id": 10,
        "name": "Carlos Gabriel Duarte Ortiz",
        "email": "carlosgabriel.1@hotmail.com"
    },
    {
        "id": 11,
        "name": "Carlos Leonardo Duarte Ortiz",
        "email": "carlosleonardo.1@hotmail.com"
    },
    {
        "id": 12,
        "name": "Miguel Ángel Duarte Ortiz",
        "email": "miguelangel.1@hotmail.com"
    },
    {
        "id": 13,
        "name": "Joaquin Miguel Duarte Ortiz",
        "email": "joaquinmiguel.1@hotmail.com"
    },
    {
        "id": 14,
        "name": "Antonio Raúl Duarte Ortiz",
        "email": "antonioraul.1@hotmail.com"
    },
    {
        "id": 15,
        "name": "Eduardo Manuel Duarte Ortiz",
        "email": "eduardomanuel.1@hotmail.com"
    },
    {
        "id": 16,
        "name": "Carlos Aaron Duarte Ortiz",
        "email": "carlosaaron.1@hotmail.com"
    },
    {
        "id": 17,
        "name": "Carlos Armando Duarte Ortiz",
        "email": "carlosarmando.1@hotmail.com"
    },
    {
        "id": 18,
        "name": "Ana Luisa Duarte Ortiz",
        "email": "analuisa.1@hotmail.com"
    },
    {
        "id": 19,
        "name": "Erica Rosa Duarte Ortiz",
        "email": "ericarosa.1@hotmail.com"
    },
    {
        "id": 20,
        "name": "Alma Lorena Duarte Ortiz",
        "email": "almalorena.1@hotmail.com"
    },
    {
        "id": 21,
        "name": "Jazmin Maria Duarte Ortiz",
        "email": "jazminmaria.1@hotmail.com"
    },
    {
        "id": 22,
        "name": "Rogelio Andrés Duarte Ortiz",
        "email": "rogelioandres.1@hotmail.com"
    },
    {
        "id": 23,
        "name": "Fernando Carlos Duarte Ortiz",
        "email": "fernandocarlos.1@hotmail.com"
    },
    {
        "id": 24,
        "name": "Amanda Lucía Duarte Ortiz",
        "email": "amandalucia.1@hotmail.com"
    },
    {
        "id": 25,
        "name": "Lorena Maria Duarte Ortiz",
        "email": "lorenamaria.1@hotmail.com"
    },
    {
        "id": 26,
        "name": "Maribel González Ortiz",
        "email": "maribelgortiz.1@hotmail.com"
    },
    {
        "id": 27,
        "name": "Anastacia Angélica Duarte Ortiz",
        "email": "anastaciaangelica.1@hotmail.com"
    },
    {
        "id": 28,
        "name": "Carlos Ramiro Duarte Ortiz",
        "email": "carlosramiro.1@hotmail.com"
    },
    {
        "id": 29,
        "name": "Ramón Peralta Vega",
        "email": "ramonperaltavega.1@hotmail.com"
    },
    {
        "id": 30,
        "name": "Luis Alfonso Domínguez Pacheco",
        "email": "luisalfonso.1@hotmail.com"
    },
    {
        "id": 31,
        "name": "Luz de Luna Duarte Ortiz",
        "email": "luzdeluna.1@hotmail.com"
    },
    {
        "id": 32,
        "name": "Carlos Abel Duarte Ortiz",
        "email": "carlosabel.1@hotmail.com"
    },
    {
        "id": 33,
        "name": "Fernando Juan Duarte Ortiz",
        "email": "fernandojuan.1@hotmail.com"
    },
    {
        "id": 34,
        "name": "Isabel Erika Duarte Ortiz",
        "email": "isabelerika.1@hotmail.com"
    },
    {
        "id": 35,
        "name": "Káren Blanca Duarte Ortiz",
        "email": "karenblanca.1@hotmail.com"
    },
    {
        "id": 36,
        "name": "Carolina Solís Hernández",
        "email": "carolinasolis.1@hotmail.com"
    },
    {
        "id": 37,
        "name": "Carlos Heriberto Duarte Ortiz",
        "email": "carlosheribertoduarte.1@hotmail.com"
    },
    {
        "id": 38,
        "name": "Carlos Enrique Quijada Yépiz",
        "email": "carlosyepiz.1@hotmail.com"
    },
    {
        "id": 39,
        "name": "Carlos Humberto Duarte Ortiz",
        "email": "carloshumberto.1@hotmail.com"
    },
    {
        "id": 40,
        "name": "Carlos Esteban Duarte Ortiz",
        "email": "carlosesteban.1@hotmail.com"
    },
    {
        "id": 41,
        "name": "Carlos Hernán Duarte Ortiz",
        "email": "carloshernan.1@hotmail.com"
    },
    {
        "id": 42,
        "name": "Juan Alfonso Duarte Ortiz",
        "email": "juanalfonso.1@hotmail.com"
    },
    {
        "id": 43,
        "name": "César Alberto Duarte Ortiz",
        "email": "cesarduarte.1@hotmail.com"
    },
    {
        "id": 44,
        "name": "Julio César Duarte Ortiz",
        "email": "juliocesar.1@hotmail.com"
    },
    {
        "id": 45,
        "name": "Carlos Marco Duarte Ortiz",
        "email": "carlosmarco.1@hotmail.com"
    },
    {
        "id": 46,
        "name": "Carlos Aurelio Duarte Ortiz",
        "email": "carlosaurelio.1@hotmail.com"
    },
    {
        "id": 47,
        "name": "Ana Sofía Duarte Ortiz",
        "email": "anasofia.1@hotmail.com"
    },
    {
        "id": 48,
        "name": "Alma Guadalupe Duarte Ortiz",
        "email": "almaguadalupe.1@hotmail.com"
    },
    {
        "id": 49,
        "name": "Almendra Quijada Ortiz",
        "email": "almendraortiz.1@hotmail.com"
    },
    {
        "id": 50,
        "name": "Deborah Lucía Duarte Ortiz",
        "email": "deborahlucia.1@hotmail.com"
    }
]